event_tracking-3.3.0.dist-info/licenses/AUTHORS
event_tracking-3.3.0.dist-info/licenses/LICENSE.TXT
eventtracking/__init__.py
eventtracking/config.py
eventtracking/exceptions.py
eventtracking/handlers.py
eventtracking/locator.py
eventtracking/tasks.py
eventtracking/tracker.py
eventtracking/backends/__init__.py
eventtracking/backends/async_routing.py
eventtracking/backends/event_bus.py
eventtracking/backends/logger.py
eventtracking/backends/mongodb.py
eventtracking/backends/routing.py
eventtracking/backends/segment.py
eventtracking/backends/tests/__init__.py
eventtracking/backends/tests/test_async_routing.py
eventtracking/backends/tests/test_event_bus.py
eventtracking/backends/tests/test_logger.py
eventtracking/backends/tests/test_logger_integration.py
eventtracking/backends/tests/test_mongodb.py
eventtracking/backends/tests/test_mongodb_integration.py
eventtracking/backends/tests/test_mongodb_performance.py
eventtracking/backends/tests/test_routing.py
eventtracking/backends/tests/test_segment.py
eventtracking/django/__init__.py
eventtracking/django/apps.py
eventtracking/django/django_tracker.py
eventtracking/django/tests/__init__.py
eventtracking/django/tests/settings.py
eventtracking/django/tests/test_configuration.py
eventtracking/django/tests/test_models.py
eventtracking/processors/__init__.py
eventtracking/processors/exceptions.py
eventtracking/processors/regex_filter.py
eventtracking/processors/whitelist.py
eventtracking/processors/tests/__init__.py
eventtracking/processors/tests/test_regex_filter.py
eventtracking/processors/tests/test_whitelist.py
eventtracking/tests/__init__.py
eventtracking/tests/test_handlers.py
eventtracking/tests/test_locator.py
eventtracking/tests/test_tasks.py
eventtracking/tests/test_track.py
event_tracking-3.3.0.dist-info/METADATA
event_tracking-3.3.0.dist-info/WHEEL
event_tracking-3.3.0.dist-info/top_level.txt
event_tracking-3.3.0.dist-info/RECORD
