Metadata-Version: 2.4
Name: event-tracking
Version: 3.3.0
Summary: A simple event tracking system.
Home-page: https://github.com/openedx/event-tracking
Author: edX
Author-email: oscm@edx.org
License: AGPLv3 License
Classifier: Development Status :: 2 - Pre-Alpha
Classifier: Environment :: Web Environment
Classifier: Framework :: Django
Classifier: Framework :: Django :: 4.2
Classifier: Framework :: Django :: 5.2
Classifier: Intended Audience :: Developers
Classifier: Operating System :: OS Independent
Classifier: Programming Language :: Python
Classifier: Programming Language :: Python :: 3
Classifier: Programming Language :: Python :: 3.11
Classifier: Programming Language :: Python :: 3.12
Classifier: Topic :: Internet :: WWW/HTTP
Classifier: Topic :: Internet :: WWW/HTTP :: Dynamic Content
License-File: LICENSE.TXT
License-File: AUTHORS
Requires-Dist: celery<6.0
Requires-Dist: django
Requires-Dist: edx-django-utils
Requires-Dist: edx-toggles
Requires-Dist: openedx-events>=9.5.1
Requires-Dist: pymongo>=4.0.0
Requires-Dist: pytz
Requires-Dist: six
Dynamic: author
Dynamic: author-email
Dynamic: classifier
Dynamic: description
Dynamic: home-page
Dynamic: license
Dynamic: license-file
Dynamic: requires-dist
Dynamic: summary
